pjtools/__init__.py
pjtools/registries.py
pjtools/version.py
pjtools/configurator/__init__.py
pjtools/configurator/base.py
pjtools/configurator/configurator.py
pjtools/configurator/dumper.py
pjtools/database/__init__.py
pjtools/database/auto_database.py
pjtools/database/base.py
pjtools/database/sqlite_wrapper.py
pjtools/registry/__init__.py
pjtools/registry/registry.py
pjtools-0.0.3.dist-info/LICENSE
pjtools-0.0.3.dist-info/METADATA
pjtools-0.0.3.dist-info/WHEEL
pjtools-0.0.3.dist-info/top_level.txt
pjtools-0.0.3.dist-info/RECORD
