Metadata-Version: 2.1
Name: pjtools
Version: 0.0.3
Summary: UNKNOWN
Home-page: UNKNOWN
Author: Xinyu Wang
Author-email: wangxinyu2017@gmail.com
License: UNKNOWN
Platform: UNKNOWN
Requires-Dist: numpy
Requires-Dist: pyyaml
